jupyterlab_nebari_mode/__init__.py
jupyterlab_nebari_mode/_version.py
jupyterlab_nebari_mode-0.3.0.data/data/share/jupyter/labextensions/jupyterlab-nebari-mode/package.json
jupyterlab_nebari_mode-0.3.0.data/data/share/jupyter/labextensions/jupyterlab-nebari-mode/static/388.a55ea4aace02879f4e8f.js
jupyterlab_nebari_mode-0.3.0.data/data/share/jupyter/labextensions/jupyterlab-nebari-mode/static/728.1c85c64a5f9c67322320.js
jupyterlab_nebari_mode-0.3.0.data/data/share/jupyter/labextensions/jupyterlab-nebari-mode/static/remoteEntry.afe799a610e9ca5544e8.js
jupyterlab_nebari_mode-0.3.0.data/data/share/jupyter/labextensions/jupyterlab-nebari-mode/static/style.js
jupyterlab_nebari_mode-0.3.0.data/data/share/jupyter/labextensions/jupyterlab-nebari-mode/static/third-party-licenses.json
jupyterlab_nebari_mode-0.3.0.data/data/share/jupyter/labextensions/jupyterlab-nebari-mode/install.json
jupyterlab_nebari_mode-0.3.0.dist-info/METADATA
jupyterlab_nebari_mode-0.3.0.dist-info/WHEEL
jupyterlab_nebari_mode-0.3.0.dist-info/licenses/LICENSE
jupyterlab_nebari_mode-0.3.0.dist-info/RECORD
