Metadata-Version: 2.3
Name: jupyterlab_nebari_mode
Version: 0.3.0
Dynamic: Keywords
Summary: Nebari customizations for JupyterLab.
Project-URL: Homepage, https://github.com/nebari-dev/jupyterlab-nebari-mode
Project-URL: Bug Tracker, https://github.com/nebari-dev/jupyterlab-nebari-mode/issues
Project-URL: Repository, https://github.com/nebari-dev/jupyterlab-nebari-mode.git
Author-email: Nebari development team <internal-it@quansight.com>
License: BSD 3-Clause License
License-File: LICENSE
Classifier: Framework :: Jupyter
Classifier: Framework :: Jupyter :: JupyterLab
Classifier: Framework :: Jupyter :: JupyterLab :: 4
Classifier: Framework :: Jupyter :: JupyterLab :: Extensions
Classifier: Framework :: Jupyter :: JupyterLab :: Extensions :: Prebuilt
Classifier: License :: OSI Approved :: BSD License
Classifier: Programming Language :: Python
Classifier: Programming Language :: Python :: 3
Classifier: Programming Language :: Python :: 3.8
Classifier: Programming Language :: Python :: 3.9
Classifier: Programming Language :: Python :: 3.10
Classifier: Programming Language :: Python :: 3.11
Classifier: Programming Language :: Python :: 3.12
Requires-Python: >=3.8
Provides-Extra: integration-test
Requires-Dist: jupyter-server-proxy; extra == 'integration-test'
Requires-Dist: jupyter-vscode-proxy; extra == 'integration-test'
